Workbook

Sheet Resumen
A1: Resumen de ejecución · Angie Tech
A2: Fecha: 2026-10-12 · Fuente: hoja de casos de uso compartida por la usuaria · Los conteos se calculan con fórmulas sobre la hoja «Casos de prueba».
A4: Estado | B4: Casos | C4: %
A5: Aprobado | B5: =COUNTIF('Casos de prueba'!$J$2:$J$108,A5) -> 92 | C5: =IFERROR(B5/$B$10,0) -> 0.85981308
A6: Corregido | B6: =COUNTIF('Casos de prueba'!$J$2:$J$108,A6) -> 14 | C6: =IFERROR(B6/$B$10,0) -> 0.13084112
A7: Corregido (falta ejecutar SQL 05) | B7: =COUNTIF('Casos de prueba'!$J$2:$J$108,A7) -> 0 | C7: =IFERROR(B7/$B$10,0) -> 0
A8: Fallido | B8: =COUNTIF('Casos de prueba'!$J$2:$J$108,A8) -> 0 | C8: =IFERROR(B8/$B$10,0) -> 0
A9: No ejecutado | B9: =COUNTIF('Casos de prueba'!$J$2:$J$108,A9) -> 1 | C9: =IFERROR(B9/$B$10,0) -> 0.0093457944
A10: Total | B10: =SUM(B5:B9) -> 107 | C10: =SUM(C5:C9) -> 1
A12: Módulo | B12: Casos | C12: Aprobados | D12: Corregidos | E12: Fallidos / no ejecutados
A13: Autenticación y permisos | B13: =COUNTIF('Casos de prueba'!$B$2:$B$108,A13) -> 10 | C13: =COUNTIFS('Casos de prueba'!$B$2:$B$108,A13,'Casos de prueba'!$J$2:$J$108,"Aprobado") -> 9 | D13: =COUNTIFS('Casos de prueba'!$B$2:$B$108,A13,'Casos de prueba'!$J$2:$J$108,"Corregido*") -> 1 | E13: =B13-C13-D13 -> 0
A14: Dashboard e Inicio | B14: =COUNTIF('Casos de prueba'!$B$2:$B$108,A14) -> 12 | C14: =COUNTIFS('Casos de prueba'!$B$2:$B$108,A14,'Casos de prueba'!$J$2:$J$108,"Aprobado") -> 11 | D14: =COUNTIFS('Casos de prueba'!$B$2:$B$108,A14,'Casos de prueba'!$J$2:$J$108,"Corregido*") -> 1 | E14: =B14-C14-D14 -> 0
A15: Inventario | B15: =COUNTIF('Casos de prueba'!$B$2:$B$108,A15) -> 18 | C15: =COUNTIFS('Casos de prueba'!$B$2:$B$108,A15,'Casos de prueba'!$J$2:$J$108,"Aprobado") -> 18 | D15: =COUNTIFS('Casos de prueba'!$B$2:$B$108,A15,'Casos de prueba'!$J$2:$J$108,"Corregido*") -> 0 | E15: =B15-C15-D15 -> 0
A16: Ventas y carrito | B16: =COUNTIF('Casos de prueba'!$B$2:$B$108,A16) -> 14 | C16: =COUNTIFS('Casos de prueba'!$B$2:$B$108,A16,'Casos de prueba'!$J$2:$J$108,"Aprobado") -> 12 | D16: =COUNTIFS('Casos de prueba'!$B$2:$B$108,A16,'Casos de prueba'!$J$2:$J$108,"Corregido*") -> 2 | E16: =B16-C16-D16 -> 0
A17: Facturación | B17: =COUNTIF('Casos de prueba'!$B$2:$B$108,A17) -> 15 | C17: =COUNTIFS('Casos de prueba'!$B$2:$B$108,A17,'Casos de prueba'!$J$2:$J$108,"Aprobado") -> 12 | D17: =COUNTIFS('Casos de prueba'!$B$2:$B$108,A17,'Casos de prueba'!$J$2:$J$108,"Corregido*") -> 3 | E17: =B17-C17-D17 -> 0
A18: Clientes | B18: =COUNTIF('Casos de prueba'!$B$2:$B$108,A18) -> 8 | C18: =COUNTIFS('Casos de prueba'!$B$2:$B$108,A18,'Casos de prueba'!$J$2:$J$108,"Aprobado") -> 7 | D18: =COUNTIFS('Casos de prueba'!$B$2:$B$108,A18,'Casos de prueba'!$J$2:$J$108,"Corregido*") -> 1 | E18: =B18-C18-D18 -> 0
A19: Empleados y permisos | B19: =COUNTIF('Casos de prueba'!$B$2:$B$108,A19) -> 8 | C19: =COUNTIFS('Casos de prueba'!$B$2:$B$108,A19,'Casos de prueba'!$J$2:$J$108,"Aprobado") -> 7 | D19: =COUNTIFS('Casos de prueba'!$B$2:$B$108,A19,'Casos de prueba'!$J$2:$J$108,"Corregido*") -> 1 | E19: =B19-C19-D19 -> 0
A20: Proveedores y compras | B20: =COUNTIF('Casos de prueba'!$B$2:$B$108,A20) -> 6 | C20: =COUNTIFS('Casos de prueba'!$B$2:$B$108,A20,'Casos de prueba'!$J$2:$J$108,"Aprobado") -> 6 | D20: =COUNTIFS('Casos de prueba'!$B$2:$B$108,A20,'Casos de prueba'!$J$2:$J$108,"Corregido*") -> 0 | E20: =B20-C20-D20 -> 0
A21: Interfaz y experiencia | B21: =COUNTIF('Casos de prueba'!$B$2:$B$108,A21) -> 10 | C21: =COUNTIFS('Casos de prueba'!$B$2:$B$108,A21,'Casos de prueba'!$J$2:$J$108,"Aprobado") -> 5 | D21: =COUNTIFS('Casos de prueba'!$B$2:$B$108,A21,'Casos de prueba'!$J$2:$J$108,"Corregido*") -> 4 | E21: =B21-C21-D21 -> 1
A22: Integridad y seguridad transversal | B22: =COUNTIF('Casos de prueba'!$B$2:$B$108,A22) -> 6 | C22: =COUNTIFS('Casos de prueba'!$B$2:$B$108,A22,'Casos de prueba'!$J$2:$J$108,"Aprobado") -> 5 | D22: =COUNTIFS('Casos de prueba'!$B$2:$B$108,A22,'Casos de prueba'!$J$2:$J$108,"Corregido*") -> 1 | E22: =B22-C22-D22 -> 0

Sheet Casos de prueba
A1: ID | B1: Módulo | C1: Caso de prueba | D1: Precondiciones / datos | E1: Pasos de ejecución | F1: Resultado esperado | G1: Prioridad | H1: Rol | I1: Tipo | J1: Estado | K1: Resultado obtenido | L1: Evidencia / defecto | M1: Ejecutado por | N1: Fecha de ejecución
A2: AUT-001 | B2: Autenticación y permisos | C2: Inicio de sesión válido como administrador | D2: Administrador activo. | E2: Abrir login; ingresar credenciales válidas; entrar. | F2: Accede al Inicio administrativo y ve módulos autorizados. | G2: Crítica | H2: Administrador | I2: Funcional | J2: Aprobado | K2: UI: entra al Inicio administrativo «Administrador · Controla tu negocio» con módulos Inventario, Facturación, Clientes, Ventas, Ingresos, Gastos. | L2: Navegador localhost:5173 | M2: Claude (QA automatizado) | N2: 2026-10-12
A3: AUT-002 | B3: Autenticación y permisos | C3: Inicio de sesión válido como vendedor | D3: Vendedor activo. | E3: Abrir login; ingresar credenciales válidas; entrar. | F3: Accede al Inicio de vendedor sin información administrativa. | G3: Crítica | H3: Vendedor | I3: Funcional | J3: Aprobado | K3: UI: entra a Inicio de vendedor «Vende de forma rápida»; sin ingresos globales, gastos, utilidad ni comisiones. | L3: Navegador | M3: Claude (QA automatizado) | N3: 2026-10-12
A4: AUT-003 | B4: Autenticación y permisos | C4: Contraseña incorrecta | D4: Usuario de QA existente. | E4: Ingresar correo válido y contraseña incorrecta. | F4: Deniega acceso y muestra mensaje claro. | G4: Alta | H4: Ambos | I4: Seguridad | J4: Aprobado | K4: HTTP 400: Invalid login credentials; UI traduce a «Correo o contraseña incorrectos.» | L4: mensajeError() en format.js | M4: Claude (QA automatizado) | N4: 2026-10-12
A5: AUT-004 | B5: Autenticación y permisos | C5: Campos obligatorios vacíos | D5: Pantalla de login. | E5: Enviar formulario vacío. | F5: Indica campos obligatorios y no inicia sesión. | G5: Alta | H5: Ambos | I5: Funcional | J5: Aprobado | K5: Formulario vacío: el navegador marca «Completa este campo» en correo y contraseña; no inicia sesión (sigue en /login). | L5: validación required | M5: Claude (QA automatizado) | N5: 2026-10-12
A6: AUT-005 | B6: Autenticación y permisos | C6: Cerrar sesión | D6: Sesión iniciada. | E6: Cerrar sesión e intentar volver con Atrás. | F6: La sesión termina y las pantallas privadas exigen autenticación. | G6: Crítica | H6: Ambos | I6: Seguridad | J6: Aprobado | K6: Cerrar sesión → /login; Atrás → /login; abrir /facturas directo → /login; no queda token guardado. | L6: ProtectedRoute | M6: Claude (QA automatizado) | N6: 2026-10-12
A7: AUT-006 | B7: Autenticación y permisos | C7: Vendedor abre ruta administrativa | D7: Sesión de vendedor; ruta conocida. | E7: Abrir URL administrativa y probar API si aplica. | F7: Deniega acceso en interfaz y servidor; no filtra datos. | G7: Crítica | H7: Vendedor | I7: Seguridad | J7: Aprobado | K7: movimientos:0; compras:0; pagos_proveedor:0; actividad:0; compra_items:0; movimientos_inventario:0; resumen_dashboard:400; productos(costos):0 | L7: API REST con token de vendedor | M7: Claude (QA automatizado) | N7: 2026-10-12
A8: AUT-007 | B8: Autenticación y permisos | C8: Vendedor intenta editar precio o stock | D8: Vendedor sin permiso. | E8: Intentar editar desde UI y solicitud directa. | F8: Operación rechazada en servidor; datos intactos. | G8: Crítica | H8: Vendedor | I8: Seguridad | J8: Aprobado | K8: PATCH precio → 200 filas=0; ajuste → 400 «No tienes permiso para modificar el inventario»; PATCH stock → 200; precio y stock intactos (3650000, 0) | L8: UI vendedor sin Editar/Cargar | M8: Claude (QA automatizado) | N8: 2026-10-12
A9: AUT-008 | B9: Autenticación y permisos | C9: Recuperación de contraseña | D9: Correo de QA habilitado. | E9: Solicitar recuperación y completar el flujo. | F9: Flujo funciona sin revelar datos sensibles de cuentas. | G9: Media | H9: Ambos | I9: Funcional | J9: Corregido | K9: Antes no existía: «¿Olvidaste tu contraseña?» solo decía «pídele al administrador», que no tenía cómo hacerlo. Ahora envía un enlace al correo y la página /restablecer permite crear la contraseña nueva (mínimo 8, confirmación). No revela si el correo existe. Probado hasta la pantalla de nueva contraseña; el correo real no se envió. | L9: Login.jsx, Restablecer.jsx. Requiere en Supabase > Authentication > URL Configuration agregar la URL de la app + /restablecer. | M9: Claude (QA automatizado) | N9: 2026-10-12
A10: AUT-009 | B10: Autenticación y permisos | C10: Acceso de empleado desactivado | D10: Empleado desactivado. | E10: Intentar iniciar sesión y usar sesión previa. | F10: Se bloquea el acceso según política de sesiones. | G10: Crítica | H10: Administrador | I10: Seguridad | J10: Aprobado | K10: Igual que EMP-002: el acceso a datos y operaciones queda bloqueado al instante, también con la sesión ya abierta. | M10: Claude (QA automatizado) | N10: 2026-10-12
A11: AUT-010 | B11: Autenticación y permisos | C11: Sesión expirada | D11: Token/sesión expirados en QA. | E11: Intentar navegar o guardar tras expirar. | F11: Solicita autenticación y no ejecuta operaciones protegidas. | G11: Alta | H11: Ambos | I11: Seguridad | J11: Aprobado | K11: Lectura con token vencido → 401 «JWT cryptographic operation failed»; emitir factura → 401 | L11: supabase-js refresca o devuelve a /login | M11: Claude (QA automatizado) | N11: 2026-10-12
A12: DAS-001 | B12: Dashboard e Inicio | C12: Ventas del día | D12: Ventas en distintas fechas. | E12: Consultar total del día. | F12: Coincide con ventas del día y regla definida de estados. | G12: Alta | H12: Administrador | I12: Funcional | J12: Aprobado | K12: Dashboard hoy 26305000 / 3 facturas = recálculo 26305000 / 3 (solo emitidas, neto de devoluciones) | L12: resumen_dashboard vs facturas_netas | M12: Claude (QA automatizado) | N12: 2026-10-12
A13: DAS-002 | B13: Dashboard e Inicio | C13: Filtro de ventas día/mes/año | D13: Ventas en varios períodos. | E13: Cambiar filtro y comparar resultados. | F13: Importe y contador corresponden al período seleccionado. | G13: Alta | H13: Administrador | I13: Funcional | J13: Aprobado | K13: Mes 75770000 (18 fact.), año 75770000; dashboard mes 75770000 | L13: Recálculo por período | M13: Claude (QA automatizado) | N13: 2026-10-12
A14: DAS-003 | B14: Dashboard e Inicio | C14: Ingresos y gastos | D14: Movimientos registrados. | E14: Comparar métricas con registros fuente. | F14: Valores correctos y no confundidos con ventas. | G14: Alta | H14: Administrador | I14: Funcional | J14: Aprobado | K14: Ingreso 7.000 → ingresos +7000; gasto 3.000 → gastos +3000; ventas sin cambio (+0). Movimientos QA eliminados. | L14: resumen_dashboard | M14: Claude (QA automatizado) | N14: 2026-10-12
A15: DAS-004 | B15: Dashboard e Inicio | C15: Valor del inventario | D15: Productos con costos y stock diferentes. | E15: Consultar total y comparar fórmula acordada. | F15: Valor corresponde a regla aprobada, por ejemplo costo × stock. | G15: Alta | H15: Administrador | I15: Funcional | J15: Aprobado | K15: Valor inventario 24993500 = Σ costo × stock (24993500) | L15: Fórmula costo × stock de productos activos | M15: Claude (QA automatizado) | N15: 2026-10-12
A16: DAS-005 | B16: Dashboard e Inicio | C16: Productos con stock bajo | D16: Productos debajo, igual y encima del mínimo. | E16: Consultar sección de stock bajo. | F16: Lista solo productos que cumplen la regla de mínimo. | G16: Alta | H16: Administrador | I16: Funcional | J16: Aprobado | K16: 2 productos con stock ≤ mínimo (recálculo 2) | L16: vista stock_bajo | M16: Claude (QA automatizado) | N16: 2026-10-12
A17: DAS-006 | B17: Dashboard e Inicio | C17: Ventas por empleado | D17: Dos vendedores con ventas. | E17: Filtrar reporte por período. | F17: Totales correctos por vendedor. | G17: Alta | H17: Administrador | I17: Funcional | J17: Aprobado | K17: Administrador de prueba: 41055000 (11 fact.); Vendedor de prueba: 28860000 (5 fact.); José Aldana: 5855000 (2 fact.) = recálculo por vendedor | L17: rpc ventas_por_empleado | M17: Claude (QA automatizado) | N17: 2026-10-12
A18: DAS-007 | B18: Dashboard e Inicio | C18: Facturas realizadas | D18: Facturas emitidas/anuladas y fechas distintas. | E18: Comparar contador con regla de estados y período. | F18: Contador correcto según especificación. | G18: Alta | H18: Administrador | I18: Funcional | J18: Aprobado | K18: Contador del mes 18 = 18 emitidas (excluye 4 anuladas) | M18: Claude (QA automatizado) | N18: 2026-10-12
A19: DAS-008 | B19: Dashboard e Inicio | C19: Dashboard sin movimientos | D19: Entorno QA vacío. | E19: Abrir dashboard. | F19: Muestra ceros/estados vacíos sin errores. | G19: Media | H19: Administrador | I19: Usabilidad | J19: Aprobado | K19: Mes sin movimientos (mayo 2025): Ventas $0 · 0 facturas, Ingresos $0, Gastos $0, sin errores. | L19: Inicio admin, selector de mes | M19: Claude (QA automatizado) | N19: 2026-10-12
A20: DAS-009 | B20: Dashboard e Inicio | C20: Datos limitados a ventas propias | D20: Dos vendedores con ventas. | E20: Entrar como vendedor A y consultar resumen. | F20: Solo muestra datos autorizados de A. | G20: Crítica | H20: Vendedor | I20: Seguridad | J20: Aprobado | K20: El vendedor B no recibe ninguna venta del vendedor A (0 filas en facturas, ítems y resumen) | M20: Claude (QA automatizado) | N20: 2026-10-12
A21: DAS-010 | B21: Dashboard e Inicio | C21: Ocultar métricas administrativas al vendedor | D21: Sesión vendedor. | E21: Revisar Inicio, menús y búsquedas. | F21: No muestra ingresos globales, gastos, utilidad, valor monetario de inventario, ventas de otros ni comisiones. | G21: Crítica | H21: Vendedor | I21: Seguridad | J21: Aprobado | K21: Vendedor: Inicio, Inventario, Vender, Facturas, Historial, Clientes y Más sin «comisión», «utilidad», «gastos», «valor del inventario», «ingresos globales» ni costos. /finanzas, /proveedores, /empleados redirigen a Inicio. | L21: Búsqueda de texto en 9 pantallas | M21: Claude (QA automatizado) | N21: 2026-10-12
A22: DAS-011 | B22: Dashboard e Inicio | C22: Últimas facturas del vendedor | D22: Facturas de varios vendedores. | E22: Consultar últimas facturas. | F22: Solo muestra facturas autorizadas por política. | G22: Alta | H22: Vendedor | I22: Seguridad | J22: Aprobado | K22: «Mis últimas facturas» muestra solo FV-0019…0023 del propio vendedor; el filtro por vendedor_id se aplica en servidor y cliente. | L22: sellerHome.js + RLS | M22: Claude (QA automatizado) | N22: 2026-10-12
A23: DAS-012 | B23: Dashboard e Inicio | C23: Filtro de ventas propias | D23: Ventas del vendedor en distintos períodos. | E23: Cambiar día/mes/año. | F23: Refleja ventas propias del período elegido. | G23: Alta | H23: Vendedor | I23: Funcional | J23: Corregido | K23: Antes solo había Hoy / Esta semana / Este mes (faltaba año). Se agregó «Este año» con comparación vs. año anterior. Hoy $26.305.000 (3) · Mes y Año $28.860.000 (5) = API. | L23: InicioVendedor.jsx, sellerHome.js | M23: Claude (QA automatizado) | N23: 2026-10-12
A24: INV-001 | B24: Inventario | C24: Crear producto válido | D24: Formulario disponible. | E24: Completar campos obligatorios y guardar. | F24: Producto guardado y visible en inventario. | G24: Crítica | H24: Administrador / Vendedor | I24: Funcional | J24: Aprobado | K24: Productos creados: QA-FUNDA-IP15-NEG y QA-CABLE-USBC | L24: POST productos (admin) | M24: Claude (QA automatizado) | N24: 2026-10-12
A25: INV-002 | B25: Inventario | C25: Crear producto sin foto | D25: Imagen opcional. | E25: Crear producto sin adjuntar imagen. | F25: Permite guardar y muestra placeholder uniforme. | G25: Alta | H25: Administrador / Vendedor | I25: Funcional | J25: Aprobado | K25: Guardado sin foto_url (null); la tarjeta usa el placeholder común | L25: foto_url null | M25: Claude (QA automatizado) | N25: 2026-10-12
A26: INV-003 | B26: Inventario | C26: Validar campos obligatorios | D26: Formulario producto. | E26: Omitir nombre u otro campo obligatorio y guardar. | F26: Muestra validaciones y no guarda datos inválidos. | G26: Alta | H26: Administrador / Vendedor | I26: Funcional | J26: Aprobado | K26: Sin nombre → HTTP 400 «null value in column "nombre" of relation "productos" violates not-null constraint» | L26: NOT NULL nombre + validación del formulario | M26: Claude (QA automatizado) | N26: 2026-10-12
A27: INV-004 | B27: Inventario | C27: Generar SKU único | D27: SKU automático habilitado. | E27: Crear dos productos y comparar SKU. | F27: Cada producto tiene SKU único. | G27: Crítica | H27: Administrador / Vendedor | I27: Funcional | J27: Aprobado | K27: Segundo producto con el mismo SKU → HTTP 409 «duplicate key value violates unique constraint "productos_codigo_key"». La UI además busca un código libre (sufijo). | L27: unique(productos.codigo) + codigoLibre() en ProductoForm | M27: Claude (QA automatizado) | N27: 2026-10-12
A28: INV-005 | B28: Inventario | C28: Editar datos del producto | D28: Producto existente. | E28: Editar nombre/marca/modelo y guardar. | F28: Cambios persisten y se muestran correctamente. | G28: Alta | H28: Administrador / Vendedor | I28: Funcional | J28: Aprobado | K28: Tras editar y releer: {'nombre': 'QA Funda iPhone 15 Pro', 'marca': 'QA Marca', 'modelo': 'iPhone 15 Pro'} | L28: PATCH + GET | M28: Claude (QA automatizado) | N28: 2026-10-12
A29: INV-006 | B29: Inventario | C29: Guardar precios de compra y venta | D29: Producto nuevo/editable. | E29: Ingresar importes válidos y guardar. | F29: Importes correctos y visibles según permisos. | G29: Alta | H29: Administrador / Vendedor | I29: Funcional | J29: Aprobado | K29: Admin ve compra 1000 / venta 5000; vendedor ve solo precio_venta 5000 | L29: vista productos_venta sin costos | M29: Claude (QA automatizado) | N29: 2026-10-12
A30: INV-007 | B30: Inventario | C30: Categoría y compatibilidad | D30: Categorías disponibles. | E30: Crear funda para modelo específico y buscarla. | F30: Categoría, marca y compatibilidad se conservan. | G30: Alta | H30: Administrador / Vendedor | I30: Funcional | J30: Aprobado | K30: Búsqueda por modelo «iPhone 15»: [('QA Funda iPhone 15 Pro', 'Fundas', 'iPhone 15 Pro')] | L30: Categoría Fundas + modelo compatible | M30: Claude (QA automatizado) | N30: 2026-10-12
A31: INV-008 | B31: Inventario | C31: Buscar por nombre, SKU o marca | D31: Varios productos. | E31: Buscar por cada campo. | F31: Devuelve coincidencias correctas. | G31: Alta | H31: Administrador / Vendedor | I31: Funcional | J31: Aprobado | K31: Coincidencias por nombre:1, codigo:1, marca:2 | L31: Buscador de Inventario filtra nombre, SKU y marca | M31: Claude (QA automatizado) | N31: 2026-10-12
A32: INV-009 | B32: Inventario | C32: Filtros de categoría y stock | D32: Productos de varias categorías y estados. | E32: Aplicar filtros. | F32: Solo aparecen productos que cumplen criterios. | G32: Alta | H32: Administrador / Vendedor | I32: Funcional | J32: Aprobado | K32: Filtro Fundas → 2 productos, todos Fundas | L32: Hoja de filtros (categoría, marca, agotado/bajo) | M32: Claude (QA automatizado) | N32: 2026-10-12
... A40: INV-017 | B40: Inventario | C40: Validar precios inválidos | D40: Formulario producto. | E40: Ingresar precio negativo o formato inválido. | F40: Impide guardar importes inválidos. | G40: Alta | H40: Administrador / Vendedor | I40: Funcional | J40: Aprobado | K40: Precio -100 → HTTP 400 «new row for relation "productos" violates check constraint "productos_precio_venta_check"» | L40: check (precio_venta >= 0); MoneyInput solo admite dígitos | M40: Claude (QA automatizado) | N40: 2026-10-12
A41: INV-018 | B41: Inventario | C41: Persistencia de producto | D41: Producto guardado. | E41: Recargar y volver a entrar. | F41: Producto y datos permanecen guardados. | G41: Alta | H41: Administrador / Vendedor | I41: Funcional | J41: Aprobado | K41: Producto QA sigue guardado tras nueva sesión: QA Funda iPhone 15 Pro | M41: Claude (QA automatizado) | N41: 2026-10-12
A42: VEN-001 | B42: Ventas y carrito | C42: Iniciar nueva venta | D42: Sesión autorizada. | E42: Seleccionar Nueva venta. | F42: Abre flujo sin errores. | G42: Crítica | H42: Administrador / Vendedor | I42: Funcional | J42: Aprobado | K42: Nueva venta abre el punto de venta con «Tus más vendidos», categorías, marcas y buscador; sin errores. | L42: /vender | M42: Claude (QA automatizado) | N42: 2026-10-12
A43: VEN-002 | B43: Ventas y carrito | C43: Agregar producto al carrito | D43: Producto activo con stock. | E43: Buscar y agregar producto. | F43: Precio, cantidad y subtotal correctos. | G43: Crítica | H43: Administrador / Vendedor | I43: Funcional | J43: Aprobado | K43: Ítems: [(6, 2, 5000), (7, 1, 3000)]; subtotal 2×5.000 + 1×3.000 = 13000 | L43: Precio tomado del servidor | M43: Claude (QA automatizado) | N43: 2026-10-12
A44: VEN-003 | B44: Ventas y carrito | C44: Cambiar cantidad | D44: Producto en carrito y stock suficiente. | E44: Aumentar y reducir cantidad. | F44: Subtotales y total se recalculan correctamente. | G44: Alta | H44: Administrador / Vendedor | I44: Funcional | J44: Aprobado | K44: + / − recalculan: 2 → $10.000; tope en 11 = stock disponible ($55.000); al bajar vuelve a $10.000. | L44: Carrito POS | M44: Claude (QA automatizado) | N44: 2026-10-12
A45: VEN-004 | B45: Ventas y carrito | C45: Evitar vender más del stock | D45: Stock limitado. | E45: Intentar agregar cantidad superior a disponible. | F45: Bloquea exceso y explica el motivo. | G45: Crítica | H45: Administrador / Vendedor | I45: Funcional | J45: Aprobado | K45: Pedir 6 con stock 5 → HTTP 400 «Stock insuficiente para el producto 7 (disponible 5, solicitado 6)». En la UI el selector de cantidad se limita al stock. | L45: trigger de stock + POS | M45: Claude (QA automatizado) | N45: 2026-10-12
A46: VEN-005 | B46: Ventas y carrito | C46: Eliminar producto del carrito | D46: Carrito con varios productos. | E46: Eliminar una línea. | F46: Actualiza carrito y totales. | G46: Alta | H46: Administrador / Vendedor | I46: Funcional | J46: Aprobado | K46: Quitar línea pide confirmación y actualiza: 3 productos $13.000 → 2 productos $10.000. Se corrigió la tilde «Se quitarán». | L46: Vender.jsx | M46: Claude (QA automatizado) | N46: 2026-10-12
A47: VEN-006 | B47: Ventas y carrito | C47: Asociar cliente | D47: Cliente existente o creación disponible. | E47: Buscar y seleccionar cliente. | F47: Venta queda asociada al cliente correcto. | G47: Alta | H47: Administrador / Vendedor | I47: Funcional | J47: Aprobado | K47: Factura asociada al cliente 6 (QA Cliente Pruebas) | L47: facturas.cliente_id | M47: Claude (QA automatizado) | N47: 2026-10-12
A48: VEN-007 | B48: Ventas y carrito | C48: Confirmar venta válida | D48: Carrito válido y campos completos. | E48: Confirmar una vez y revisar venta/factura. | F48: Registra venta y genera factura una sola vez. | G48: Crítica | H48: Administrador / Vendedor | I48: Funcional | J48: Aprobado | K48: Factura FV19 (id 22) total 13000, cliente 6, vendedor propio | L48: rpc emitir_factura | M48: Claude (QA automatizado) | N48: 2026-10-12
A49: VEN-008 | B49: Ventas y carrito | C49: Cancelar antes de confirmar | D49: Venta en curso. | E49: Cancelar o salir. | F49: No registra venta ni descuenta stock definitivamente. | G49: Alta | H49: Administrador / Vendedor | I49: Funcional | J49: Aprobado | K49: Vaciar o quitar productos no toca el servidor; el stock solo bajó al confirmar la venta (11 → 9). | L49: Carrito local | M49: Claude (QA automatizado) | N49: 2026-10-12
A50: VEN-009 | B50: Ventas y carrito | C50: Confirmar con datos incompletos | D50: Campo obligatorio faltante. | E50: Confirmar venta. | F50: No completa operación; informa qué falta. | G50: Alta | H50: Administrador / Vendedor | I50: Funcional | J50: Corregido | K50: Sin productos → «La factura necesita al menos un producto». La app exige cliente («Falta el cliente»), pero el servidor aceptaba venta sin cliente. Corregido en emitir_factura_segura (script 05). | L50: supabase/05_reglas_venta_y_auditoria.sql · Script 05 ejecutado y verificado el 12-oct. | M50: Claude (QA automatizado) | N50: 2026-10-12
A51: VEN-010 | B51: Ventas y carrito | C51: Doble clic al confirmar | D51: Venta válida. | E51: Pulsar confirmar varias veces o reintentar. | F51: No duplica venta, factura ni movimientos. | G51: Crítica | H51: Administrador / Vendedor | I51: Funcional | J51: Aprobado | K51: Triple clic en «Cobrar»: se creó una sola factura (FV-0023). El botón se bloquea al primer toque. | L51: useAction (bloqueo síncrono) | M51: Claude (QA automatizado) | N51: 2026-10-12
A52: VEN-011 | B52: Ventas y carrito | C52: Venta de varios productos | D52: Carrito con referencias distintas. | E52: Confirmar y verificar existencias. | F52: Descuenta cantidades correctas de todos los productos. | G52: Crítica | H52: Administrador / Vendedor | I52: Funcional | J52: Aprobado | K52: Stock A 11→9 (−2), B 5→4 (−1) | L52: movimientos salida_venta | M52: Claude (QA automatizado) | N52: 2026-10-12
A53: VEN-012 | B53: Ventas y carrito | C53: Aislar ventas por vendedor | D53: Dos vendedores con ventas. | E53: Consultar Mis ventas como A. | F53: Solo muestra ventas autorizadas de A. | G53: Alta | H53: Administrador / Vendedor | I53: Seguridad | J53: Aprobado | K53: Vendedor B: facturas 0, ítems de la factura de A 0, ventas_por_empleado [] | L53: RLS facturas_select | M53: Claude (QA automatizado) | N53: 2026-10-12
... A67: FAC-012 | B67: Facturación | C67: Modificar factura emitida | D67: Factura emitida. | E67: Intentar modificar datos protegidos. | F67: Aplica restricciones y conserva trazabilidad. | G67: Alta | H67: Administrador / Vendedor | I67: Seguridad | J67: Aprobado | K67: PATCH total (admin) → 200 filas 0; PATCH ítems → 200 filas 0; DELETE → 200 filas 0; total intacto 13000 | L67: Sin políticas de update/delete en facturas | M67: Claude (QA automatizado) | N67: 2026-10-12
A68: FAC-013 | B68: Facturación | C68: Descargar factura inexistente | D68: ID inexistente. | E68: Abrir o descargar factura inexistente. | F68: Muestra error claro sin filtrar otros datos. | G68: Media | H68: Administrador / Vendedor | I68: Funcional | J68: Aprobado | K68: Consulta id inexistente → []; acción → «La factura no existe» | M68: Claude (QA automatizado) | N68: 2026-10-12
A69: FAC-014 | B69: Facturación | C69: Factura con datos extensos | D69: Cliente con nombre largo y muchos productos. | E69: Generar PDF. | F69: No corta campos esenciales ni superpone texto. | G69: Media | H69: Administrador / Vendedor | I69: Funcional | J69: Corregido | K69: Con nombre largo y 28 productos el PDF montaba textos (nombre del cliente sobre «Atendido por», descripción sobre la cantidad) y la dirección se salía del recuadro. Corregido: el texto se mide con su tamaño real y el panel crece. Verificado: 3 páginas sin cruces. | L69: invoicePdf.js | M69: Claude (QA automatizado) | N69: 2026-10-12
A70: FAC-015 | B70: Facturación | C70: Repetir anulación/devolución | D70: Factura ya anulada o devuelta. | E70: Repetir acción y recargar. | F70: No duplica movimientos ni reembolsos. | G70: Crítica | H70: Administrador / Vendedor | I70: Funcional | J70: Aprobado | K70: Devolver más de lo vendido: «Cantidad a devolver inválida para "QA Funda iPhone 15 Pro"»; anular con devoluciones: «La factura tiene devoluciones y no se puede anular»; devolver otra vez: «Cantidad a devolver inválida para "QA Cable USB-C"»; anular dos veces: «La factura ya está anulada»; stock sin | M70: Claude (QA automatizado) | N70: 2026-10-12
A71: CLI-001 | B71: Clientes | C71: Crear cliente válido | D71: Formulario disponible. | E71: Completar datos y guardar. | F71: Cliente guardado y localizable. | G71: Alta | H71: Administrador / Vendedor | I71: Funcional | J71: Aprobado | K71: Vendedor crea cliente → HTTP 201, id 6 | L71: POST clientes (permiso crear_clientes) | M71: Claude (QA automatizado) | N71: 2026-10-12
A72: CLI-002 | B72: Clientes | C72: Validar campos obligatorios | D72: Formulario cliente. | E72: Omitir campo obligatorio y guardar. | F72: Muestra validación; no guarda inválido. | G72: Alta | H72: Administrador / Vendedor | I72: Funcional | J72: Aprobado | K72: Sin documento → HTTP 400 «null value in column "documento" of relation "clientes" violates not-null constraint»; la UI pide Nombre, documento y WhatsApp (≥10 dígitos) | L72: NOT NULL documento + validación ClienteForm | M72: Claude (QA automatizado) | N72: 2026-10-12
A73: CLI-003 | B73: Clientes | C73: Buscar cliente | D73: Varios clientes existentes. | E73: Buscar por nombre/documento. | F73: Coincidencias correctas. | G73: Alta | H73: Administrador / Vendedor | I73: Funcional | J73: Aprobado | K73: Coincidencias: nombre:1, documento:1 | L73: Buscador de Clientes y ClientePicker | M73: Claude (QA automatizado) | N73: 2026-10-12
A74: CLI-004 | B74: Clientes | C74: Guardar correo y teléfono | D74: Formulario cliente. | E74: Ingresar datos válidos y guardar. | F74: Datos persisten con formato correcto. | G74: Alta | H74: Administrador / Vendedor | I74: Funcional | J74: Aprobado | K74: Persistido: {'telefono': '3001112233', 'correo': 'qa.cliente@prueba.com'} | L74: GET tras guardar | M74: Claude (QA automatizado) | N74: 2026-10-12
A75: CLI-005 | B75: Clientes | C75: Historial de compras | D75: Cliente con ventas. | E75: Abrir historial. | F75: Muestra compras asociadas con permisos correctos. | G75: Alta | H75: Administrador / Vendedor | I75: Funcional | J75: Corregido | K75: Historial muestra las 5 facturas. Defecto: «Total comprado» contaba una factura devuelta por completo ($23.000 · 2 compras). Ahora $10.000 · 1 compra (neto de devoluciones). | L75: Clientes.jsx | M75: Claude (QA automatizado) | N75: 2026-10-12
A76: CLI-006 | B76: Clientes | C76: Asociar cliente a factura | D76: Cliente y venta en proceso. | E76: Seleccionar cliente, confirmar y revisar factura. | F76: Factura relacionada al cliente correcto. | G76: Crítica | H76: Administrador / Vendedor | I76: Funcional | J76: Aprobado | K76: Factura FV19 enlazada al cliente id 6 | M76: Claude (QA automatizado) | N76: 2026-10-12
A77: CLI-007 | B77: Clientes | C77: Cliente duplicado | D77: Documento/correo existente. | E77: Crear otro cliente con dato duplicado. | F77: Aplica regla definida para evitar duplicados confusos. | G77: Media | H77: Administrador / Vendedor | I77: Funcional | J77: Aprobado | K77: Mismo tipo y documento → HTTP 409 «duplicate key value violates unique constraint "clientes_tipo_documento_documento_key"» → UI: «Ya existe un registro con esos datos.» | L77: unique(tipo_documento, documento) | M77: Claude (QA automatizado) | N77: 2026-10-12
A78: CLI-008 | B78: Clientes | C78: Editar contacto | D78: Cliente existente. | E78: Actualizar teléfono/correo y guardar. | F78: Cambios persisten y compras siguen vinculadas. | G78: Media | H78: Administrador / Vendedor | I78: Funcional | J78: Aprobado | K78: Editar cliente: teléfono 3001112233 → 3009998877 guardado; el historial sigue con 5 facturas. | L78: Ficha de cliente | M78: Claude (QA automatizado) | N78: 2026-10-12
A79: EMP-001 | B79: Empleados y permisos | C79: Crear empleado | D79: Administrador autorizado. | E79: Crear empleado con rol y permisos. | F79: Usuario creado con permisos asignados. | G79: Alta | H79: Administrador | I79: Funcional | J79: Aprobado | K79: Función crear-empleado → 200; perfil QA Vendedor B rol vendedor; permisos ['vender', 'ver_inventario', 'crear_clientes'] | L79: Edge Function crear-empleado + perfiles/perfil_permisos | M79: Claude (QA automatizado) | N79: 2026-10-12
A80: EMP-002 | B80: Empleados y permisos | C80: Desactivar empleado | D80: Empleado activo. | E80: Desactivar y probar acceso. | F80: Se bloquea acceso conforme a política. | G80: Crítica | H80: Administrador | I80: Seguridad | J80: Aprobado | K80: Desactivado (activo=false). Sesión previa: inventario 0 filas, vender → «No tienes permiso para vender». Login nuevo → token emitido (200) pero sin datos (clientes 0) y la app muestra «Tu usuario está desactivado». | L80: es_activo() en RLS y RPC; ProtectedRoute | M80: Claude (QA automatizado) | N80: 2026-10-12
A81: EMP-003 | B81: Empleados y permisos | C81: Modificar permisos | D81: Empleado existente. | E81: Cambiar permiso y probar función. | F81: Cambios aplican en UI y servidor. | G81: Crítica | H81: Administrador | I81: Seguridad | J81: Aprobado | K81: Sin permiso → «No tienes permiso para modificar el inventario»; al otorgar «Modificar inventario» → OK (mov 55); al quitarlo → rechazado otra vez | L81: perfil_permisos + tiene_permiso() | M81: Claude (QA automatizado) | N81: 2026-10-12
A82: EMP-004 | B82: Empleados y permisos | C82: Ventas por empleado | D82: Dos empleados con ventas. | E82: Consultar reporte como admin. | F82: Totales por empleado correctos. | G82: Alta | H82: Administrador | I82: Funcional | J82: Aprobado | K82: Administrador de prueba: 41055000 (11 fact.); Vendedor de prueba: 28860000 (5 fact.); José Aldana: 5855000 (2 fact.) | M82: Claude (QA automatizado) | N82: 2026-10-12
A83: EMP-005 | B83: Empleados y permisos | C83: Vendedor consulta ventas de otro | D83: Dos vendedores. | E83: A intenta consultar datos de B. | F83: Acceso denegado. | G83: Crítica | H83: Vendedor | I83: Seguridad | J83: Aprobado | K83: Consulta directa de datos de A con sesión de B → 0 filas | M83: Claude (QA automatizado) | N83: 2026-10-12
A84: EMP-006 | B84: Empleados y permisos | C84: No mostrar comisiones | D84: Sesión vendedor. | E84: Revisar Inicio y menús. | F84: No aparecen indicadores ni módulos de comisiones. | G84: Alta | H84: Vendedor | I84: Funcional | J84: Aprobado | K84: La interfaz del vendedor no muestra comisiones. Además se eliminaron las comisiones del sistema: no hay campo de comisión en Empleados, ni en facturas ni en el detalle del negocio, y todos los perfiles quedaron sin comisión. | L84: UI + API | M84: Claude (QA automatizado) | N84: 2026-10-12
A85: EMP-007 | B85: Empleados y permisos | C85: Proteger rutas administrativas | D85: Sesión vendedor. | E85: Abrir URL/API administrativa. | F85: Servidor deniega acceso. | G85: Crítica | H85: Vendedor | I85: Seguridad | J85: Aprobado | K85: Servidor deniega: movimientos:0; compras:0; pagos_proveedor:0; actividad:0; compra_items:0; movimientos_inventario:0; resumen_dashboard:400; productos(costos):0 | L85: Mismo set que AUT-006 + rutas /finanzas /proveedores /empleados redirigen a Inicio | M85: Claude (QA automatizado) | N85: 2026-10-12
A86: EMP-008 | B86: Empleados y permisos | C86: Historial de actividad | D86: Operaciones auditables. | E86: Realizar cambios y consultar historial. | F86: Registra actor, acción y fecha conforme al alcance. | G86: Media | H86: Administrador | I86: Funcional | J86: Corregido | K86: Ventas, anulaciones, devoluciones, inventario, compras y clientes quedan con actor, acción y fecha. Defecto: el alta de empleado quedaba sin actor y los cambios de permisos no se registraban. Corregido en script 05. | L86: auditar() + trigger en perfil_permisos · Script 05 ejecutado y verificado el 12-oct. | M86: Claude (QA automatizado) | N86: 2026-10-12
A87: PRO-001 | B87: Proveedores y compras | C87: Crear proveedor | D87: Formulario disponible. | E87: Completar datos válidos y guardar. | F87: Proveedor guardado y seleccionable. | G87: Alta | H87: Administrador | I87: Funcional | J87: Aprobado | K87: HTTP 201; proveedor id 2 | L87: Formulario simplificado: Nombre*, WhatsApp, Correo | M87: Claude (QA automatizado) | N87: 2026-10-12
A88: PRO-002 | B88: Proveedores y compras | C88: Consultar productos del proveedor | D88: Proveedor asociado a productos. | E88: Abrir detalle. | F88: Muestra productos relacionados. | G88: Alta | H88: Administrador | I88: Funcional | J88: Aprobado | K88: Productos asociados: ['QA-FUNDA-IP15-NEG', 'QA-CABLE-USBC'] | L88: productos.proveedor_id | M88: Claude (QA automatizado) | N88: 2026-10-12
A89: PRO-003 | B89: Proveedores y compras | C89: Registrar compra/ingreso | D89: Proveedor/productos existentes; flujo implementado. | E89: Registrar compra y verificar stock. | F89: Relación con proveedor y actualización de stock única. | G89: Alta | H89: Administrador | I89: Funcional | J89: Aprobado | K89: Compra 2 a crédito; stock A 0→10, B 0→5 (una sola vez) | L89: rpc registrar_compra | M89: Claude (QA automatizado) | N89: 2026-10-12
A90: PRO-004 | B90: Proveedores y compras | C90: Historial de compras | D90: Proveedor con compras. | E90: Abrir historial. | F90: Compras, fechas y valores correctos. | G90: Alta | H90: Administrador | I90: Funcional | J90: Aprobado | K90: Historial: [{'id': 2, 'fecha': '2026-10-12', 'total': 12500, 'numero_documento': 'QA-001'}] | L90: Ficha del proveedor > Compras | M90: Claude (QA automatizado) | N90: 2026-10-12
A91: PRO-005 | B91: Proveedores y compras | C91: Cuentas por pagar | D91: Módulo implementado y datos de prueba. | E91: Consultar saldos/vencimientos. | F91: Saldos y estados coinciden con compras y pagos. | G91: Alta | H91: Administrador | I91: Funcional | J91: Aprobado | K91: Saldo 12.500 (vence 2026-11-12) → abono 5.000 → 7.500; abono excesivo rechazado «El abono debe ser mayor que 0 y no superar el saldo (7500)»; pago final → 0 | L91: compras_saldo + registrar_pago_proveedor | M91: Claude (QA automatizado) | N91: 2026-10-12
A92: PRO-006 | B92: Proveedores y compras | C92: Validar proveedor incompleto | D92: Formulario proveedor. | E92: Omitir campo obligatorio y guardar. | F92: Muestra validación y no guarda inválido. | G92: Media | H92: Administrador | I92: Funcional | J92: Aprobado | K92: Sin nombre → HTTP 400 «null value in column "nombre" of relation "proveedores" violates not-null constraint»; la UI exige Nombre* | L92: NOT NULL en proveedores.nombre | M92: Claude (QA automatizado) | N92: 2026-10-12
A93: UI-001 | B93: Interfaz y experiencia | C93: Cambiar modo claro/oscuro | D93: Preferencia de tema disponible. | E93: Cambiar tema y recorrer módulos. | F93: Actualiza colores sin alterar datos/funciones. | G93: Alta | H93: Administrador / Vendedor | I93: Usabilidad | J93: Aprobado | K93: Cambio claro ↔ oscuro: data-theme cambia, fondos y textos se actualizan, sin recargar ni perder datos. | L93: ThemeToggle | M93: Claude (QA automatizado) | N93: 2026-10-12
A94: UI-002 | B94: Interfaz y experiencia | C94: Banner por rol y tema | D94: Roles y temas disponibles. | E94: Abrir Inicio en ambos roles y temas. | F94: Banner/contenido correcto según rol; contraste adecuado. | G94: Alta | H94: Administrador / Vendedor | I94: Usabilidad | J94: Corregido | K94: Admin: banner «Administrador · Controla tu negocio» en ambos temas, pero el título salía «Administrad…» en celulares (corregido). Vendedor: su Inicio no mostraba el banner de rol (corregido, imagen clara y oscura). | L94: luxe.css, InicioVendedor.jsx | M94: Claude (QA automatizado) | N94: 2026-10-12
A95: UI-003 | B95: Interfaz y experiencia | C95: Navegación entre módulos | D95: Sesión activa. | E95: Usar navegación principal. | F95: Abre pantalla correcta y respeta permisos. | G95: Alta | H95: Administrador / Vendedor | I95: Usabilidad | J95: Aprobado | K95: 12 rutas de admin y 9 de vendedor abren correctamente; rutas sin permiso redirigen a Inicio. | L95: Navegación | M95: Claude (QA automatizado) | N95: 2026-10-12
... A102: UI-010 | B102: Interfaz y experiencia | C102: Formato de moneda y fecha | D102: Configuración regional acordada. | E102: Revisar importes y fechas en módulos. | F102: Formato consistente con configuración de Colombia. | G102: Media | H102: Administrador / Vendedor | I102: Usabilidad | J102: Aprobado | K102: Moneda $13.000 (es-CO, sin decimales), fechas «12 de oct de 2026 · 6:20 p. m.» en hora de Bogotá. | L102: format.js | M102: Claude (QA automatizado) | N102: 2026-10-12
A103: INT-001 | B103: Integridad y seguridad transversal | C103: Persistencia de registros | D103: Producto, cliente y venta de QA. | E103: Guardar, recargar y volver a consultar. | F103: Datos persisten sin pérdida ni duplicación. | G103: Crítica | H103: Ambos | I103: Funcional | J103: Aprobado | K103: Releídos en sesión nueva: producto «QA Funda iPhone 15 Pro», cliente «QA Cliente Pruebas», factura FV19; sin duplicados | M103: Claude (QA automatizado) | N103: 2026-10-12
A104: INT-002 | B104: Integridad y seguridad transversal | C104: Integridad venta-factura-stock | D104: Venta y stock conocidos. | E104: Registrar venta y revisar registros relacionados. | F104: Importes/cantidades coinciden en venta, factura y stock. | G104: Crítica | H104: Ambos | I104: Funcional | J104: Aprobado | K104: Factura total 13000 = Σ ítems; movimientos [(6, -2), (7, -1)] = ítems | L104: facturas / factura_items / movimientos_inventario | M104: Claude (QA automatizado) | N104: 2026-10-12
A105: INT-003 | B105: Integridad y seguridad transversal | C105: Autorización en API | D105: Cuentas con distintos permisos. | E105: Consultar recursos con cada rol. | F105: Servidor aplica permisos de lectura/escritura. | G105: Crítica | H105: Ambos | I105: Seguridad | J105: Aprobado | K105: facturas A22/V8/anón0; clientes A6/V6/anón0; productos_venta A7/V7/anón401; productos A7/V0/anón0; movimientos A0/V0/anón0; compras A2/V0/anón0; perfiles A4/V1/anón0; actividad A75/V0/anón0 | L105: Lectura por rol (A=admin, V=vendedor). Escrituras ya cubiertas en AUT-007, FAC-010, FAC-012, EMP-003 | M105: Claude (QA automatizado) | N105: 2026-10-12
A106: INT-004 | B106: Integridad y seguridad transversal | C106: Evitar doble movimiento tras reintento | D106: Operación con posibilidad de reintento. | E106: Repetir solicitud tras timeout y revisar historial. | F106: Solo una operación lógica queda registrada. | G106: Crítica | H106: Ambos | I106: Seguridad | J106: Corregido | K106: Mismo defecto que VEN-014: dos facturas por una sola operación. Corregido con clave de idempotencia y bloqueo por clave. | L106: script 05 · Script 05 ejecutado y verificado el 12-oct. | M106: Claude (QA automatizado) | N106: 2026-10-12
A107: INT-005 | B107: Integridad y seguridad transversal | C107: Manejo de error del servidor | D107: Entorno QA con error simulable. | E107: Forzar error y revisar mensaje. | F107: Mensaje claro, sin secretos ni trazas internas. | G107: Alta | H107: Ambos | I107: Resiliencia | J107: Aprobado | K107: Datos inválidos → HTTP 400 «invalid input syntax for type bigint: "abc"»; función inexistente → 404. Sin claves ni trazas; la UI muestra mensajes amigables (mensajeError). | M107: Claude (QA automatizado) | N107: 2026-10-12
A108: INT-006 | B108: Integridad y seguridad transversal | C108: Orden y paginación | D108: Datos suficientes para varias páginas. | E108: Cambiar páginas, filtros y orden. | F108: No hay registros repetidos o perdidos. | G108: Media | H108: Ambos | I108: Funcional | J108: Aprobado | K108: 22 facturas recorridas en páginas de 5: sin repetidos ni perdidos | L108: order fecha desc, id desc | M108: Claude (QA automatizado) | N108: 2026-10-12
